odoo/addons/res_partner_industry_multi_company/README.rst
odoo/addons/res_partner_industry_multi_company/__init__.py
odoo/addons/res_partner_industry_multi_company/__manifest__.py
odoo/addons/res_partner_industry_multi_company/i18n/res_partner_industry_multi_company.pot
odoo/addons/res_partner_industry_multi_company/models/__init__.py
odoo/addons/res_partner_industry_multi_company/models/res_partner_industry.py
odoo/addons/res_partner_industry_multi_company/readme/CONTRIBUTORS.rst
odoo/addons/res_partner_industry_multi_company/readme/DESCRIPTION.rst
odoo/addons/res_partner_industry_multi_company/security/res_partner_industry.xml
odoo/addons/res_partner_industry_multi_company/static/description/icon.png
odoo/addons/res_partner_industry_multi_company/static/description/index.html
odoo/addons/res_partner_industry_multi_company/views/res_partner_industry.xml
odoo12_addon_res_partner_industry_multi_company-12.0.1.0.1.dist-info/METADATA
odoo12_addon_res_partner_industry_multi_company-12.0.1.0.1.dist-info/WHEEL
odoo12_addon_res_partner_industry_multi_company-12.0.1.0.1.dist-info/top_level.txt
odoo12_addon_res_partner_industry_multi_company-12.0.1.0.1.dist-info/RECORD
